github_ioc_scanner/__init__.py
github_ioc_scanner/async_github_client.py
github_ioc_scanner/batch_cache_coordinator.py
github_ioc_scanner/batch_cache_manager.py
github_ioc_scanner/batch_coordinator.py
github_ioc_scanner/batch_error_handler.py
github_ioc_scanner/batch_error_reporter.py
github_ioc_scanner/batch_metrics_collector.py
github_ioc_scanner/batch_models.py
github_ioc_scanner/batch_performance_analyzer.py
github_ioc_scanner/batch_progress_monitor.py
github_ioc_scanner/batch_strategy_manager.py
github_ioc_scanner/cache.py
github_ioc_scanner/cache_manager.py
github_ioc_scanner/cache_warming_manager.py
github_ioc_scanner/cli.py
github_ioc_scanner/code_analyzer.py
github_ioc_scanner/error_message_formatter.py
github_ioc_scanner/event_loop_context.py
github_ioc_scanner/exceptions.py
github_ioc_scanner/github_app_auth.py
github_ioc_scanner/github_client.py
github_ioc_scanner/improved_rate_limiting.py
github_ioc_scanner/intelligent_rate_limiter.py
github_ioc_scanner/ioc_loader.py
github_ioc_scanner/logging_config.py
github_ioc_scanner/memory_monitor.py
github_ioc_scanner/models.py
github_ioc_scanner/network_resilience.py
github_ioc_scanner/parallel_batch_processor.py
github_ioc_scanner/rate_limit_manager.py
github_ioc_scanner/resource_manager.py
github_ioc_scanner/resume_cli.py
github_ioc_scanner/retry_manager.py
github_ioc_scanner/scan_state.py
github_ioc_scanner/scanner.py
github_ioc_scanner/secrets_scanner.py
github_ioc_scanner/smart_rate_limiter.py
github_ioc_scanner/streaming_batch_processor.py
github_ioc_scanner/workflow_scanner.py
github_ioc_scanner/issues/__init__.py
github_ioc_scanner/issues/s1ngularity_nx_attack_2024.py
github_ioc_scanner/issues/shai_hulud.py
github_ioc_scanner/issues/shai_hulud_2.py
github_ioc_scanner/parsers/__init__.py
github_ioc_scanner/parsers/base.py
github_ioc_scanner/parsers/factory.py
github_ioc_scanner/parsers/go.py
github_ioc_scanner/parsers/javascript.py
github_ioc_scanner/parsers/maven.py
github_ioc_scanner/parsers/php.py
github_ioc_scanner-1.7.2.dist-info/licenses/LICENSE
github_ioc_scanner-1.7.2.dist-info/METADATA
github_ioc_scanner-1.7.2.dist-info/WHEEL
github_ioc_scanner-1.7.2.dist-info/entry_points.txt
github_ioc_scanner-1.7.2.dist-info/top_level.txt
github_ioc_scanner-1.7.2.dist-info/RECORD
