Metadata-Version: 2.4
Name: github-ioc-scanner
Version: 1.7.2
Summary: Scan GitHub repositories for Indicators of Compromise (IOCs) in package dependencies across multiple languages
Author-email: GitHub IOC Scanner Contributors <security@example.com>
License: MIT
Project-URL: Homepage, https://github.com/christianherweg0807/github_package_scanner
Project-URL: Documentation, https://github.com/christianherweg0807/github_package_scanner/tree/main/docs
Project-URL: Repository, https://github.com/christianherweg0807/github_package_scanner
Project-URL: Issues, https://github.com/christianherweg0807/github_package_scanner/issues
Project-URL: Changelog, https://github.com/christianherweg0807/github_package_scanner/blob/main/CHANGELOG.md
Keywords: security,supply-chain,ioc,github,scanner,malware,typosquatting
Classifier: Development Status :: 5 - Production/Stable
Classifier: Intended Audience :: Developers
Classifier: Intended Audience :: Information Technology
Classifier: Intended Audience :: System Administrators
Classifier: License :: OSI Approved :: MIT License
Classifier: Operating System :: OS Independent
Classifier: Programming Language :: Python :: 3
Classifier: Programming Language :: Python :: 3.8
Classifier: Programming Language :: Python :: 3.9
Classifier: Programming Language :: Python :: 3.10
Classifier: Programming Language :: Python :: 3.11
Classifier: Programming Language :: Python :: 3.12
Classifier: Topic :: Security
Classifier: Topic :: Software Development :: Quality Assurance
Classifier: Topic :: System :: Systems Administration
Classifier: Topic :: Utilities
Requires-Python: >=3.8
License-File: LICENSE
Requires-Dist: httpx>=0.24.0
Requires-Dist: pyyaml>=6.0
Requires-Dist: psutil>=5.8.0
Requires-Dist: pyjwt>=2.8.0
Requires-Dist: cryptography>=41.0.0
Provides-Extra: dev
Requires-Dist: pytest>=7.0.0; extra == "dev"
Requires-Dist: pytest-cov>=4.0.0; extra == "dev"
Requires-Dist: pytest-asyncio>=0.21.0; extra == "dev"
Requires-Dist: black>=23.0.0; extra == "dev"
Requires-Dist: isort>=5.12.0; extra == "dev"
Requires-Dist: flake8>=6.0.0; extra == "dev"
Requires-Dist: mypy>=1.0.0; extra == "dev"
Dynamic: license-file
